{
	"ambientocclusion": false,
	"textures": {
		"base": "#base",
		"particle": "#base"
	},
	"elements": [
		{
			"from": [-8, 0, 8],
			"to": [24, 32, 8],
			"rotation": {"angle": 0, "axis": "y", "origin": [8, 0, 8]},
			"shade": false,
			"faces": {
				"north": {"uv": [0, 0, 16, 16], "texture": "#base"},
				"east": {"uv": [0, 0, 0, 16], "texture": "#base"},
				"south": {"uv": [0, 0, 16, 16], "texture": "#base"},
				"west": {"uv": [0, 0, 0, 16], "texture": "#base"}
			}
		},
		{
			"from": [8, 0, -8],
			"to": [8, 32, 24],
			"rotation": {"angle": -45, "axis": "y", "origin": [8, 0, 8]},
			"shade": false,
			"faces": {
				"north": {"uv": [0, 0, 0, 16], "texture": "#base"},
				"east": {"uv": [0, 0, 16, 16], "texture": "#base"},
				"south": {"uv": [0, 0, 0, 16], "texture": "#base"},
				"west": {"uv": [0, 0, 16, 16], "texture": "#base"}
			}
		},
		{
			"from": [8, 0, -8],
			"to": [8, 32, 24],
			"rotation": {"angle": 0, "axis": "y", "origin": [8, 0, 8]},
			"shade": false,
			"faces": {
				"north": {"uv": [0, 0, 0, 16], "texture": "#base"},
				"east": {"uv": [0, 0, 16, 16], "texture": "#base"},
				"south": {"uv": [0, 0, 0, 16], "texture": "#base"},
				"west": {"uv": [0, 0, 16, 16], "texture": "#base"}
			}
		},
		{
			"from": [8, 0, -8],
			"to": [8, 32, 24],
			"rotation": {"angle": 45, "axis": "y", "origin": [8, 0, 8]},
			"shade": false,
			"faces": {
				"north": {"uv": [0, 0, 0, 16], "texture": "#base"},
				"east": {"uv": [0, 0, 16, 16], "texture": "#base"},
				"south": {"uv": [0, 0, 0, 16], "texture": "#base"},
				"west": {"uv": [0, 0, 16, 16], "texture": "#base"}
			}
		}
	]
}